LICENSE
MANIFEST.in
README.md
pyfaceau_gui.py
pyproject.toml
requirements.txt
setup.py
pyfaceau/__init__.py
pyfaceau/config.py
pyfaceau/download_weights.py
pyfaceau/parallel_pipeline.py
pyfaceau/pipeline.py
pyfaceau/processor.py
pyfaceau.egg-info/PKG-INFO
pyfaceau.egg-info/SOURCES.txt
pyfaceau.egg-info/dependency_links.txt
pyfaceau.egg-info/entry_points.txt
pyfaceau.egg-info/not-zip-safe
pyfaceau.egg-info/requires.txt
pyfaceau.egg-info/top_level.txt
pyfaceau/alignment/__init__.py
pyfaceau/alignment/calc_params.py
pyfaceau/alignment/face_aligner.py
pyfaceau/alignment/numba_calcparams_accelerator.py
pyfaceau/alignment/paw.py
pyfaceau/data/__init__.py
pyfaceau/data/hdf5_dataset.py
pyfaceau/data/quality_filter.py
pyfaceau/data/training_data_generator.py
pyfaceau/detectors/__init__.py
pyfaceau/detectors/extract_mtcnn_weights.py
pyfaceau/detectors/openface_mtcnn.py
pyfaceau/detectors/pfld.py
pyfaceau/detectors/pymtcnn_detector.py
pyfaceau/detectors/retinaface.py
pyfaceau/features/__init__.py
pyfaceau/features/histogram_median_tracker.py
pyfaceau/features/pdm.py
pyfaceau/features/triangulation.py
pyfaceau/nn/__init__.py
pyfaceau/nn/au_prediction_inference.py
pyfaceau/nn/au_prediction_net.py
pyfaceau/nn/fast_pipeline.py
pyfaceau/nn/landmark_pose_inference.py
pyfaceau/nn/landmark_pose_net.py
pyfaceau/nn/train_au_prediction.py
pyfaceau/nn/train_landmark_pose.py
pyfaceau/prediction/__init__.py
pyfaceau/prediction/au_predictor.py
pyfaceau/prediction/batched_au_predictor.py
pyfaceau/prediction/model_parser.py
pyfaceau/prediction/online_au_correction.py
pyfaceau/prediction/running_median.py
pyfaceau/prediction/running_median_fallback.py
pyfaceau/refinement/__init__.py
pyfaceau/refinement/pdm.py
pyfaceau/refinement/svr_patch_expert.py
pyfaceau/refinement/targeted_refiner.py
pyfaceau/utils/__init__.py
pyfaceau/utils/cython_extensions/cython_histogram_median.pyx
pyfaceau/utils/cython_extensions/cython_rotation_update.pyx
pyfaceau/utils/cython_extensions/setup.py