Metadata-Version: 2.4
Name: pyfaceau
Version: 1.3.9
Summary: Pure Python OpenFace 2.2 AU extraction with CLNF landmark refinement
Home-page: https://github.com/johnwilsoniv/face-analysis
Author: John Wilson
Author-email: 
License: CC BY-NC 4.0
Project-URL: Homepage, https://github.com/johnwilsoniv/pyfaceau
Project-URL: Documentation, https://github.com/johnwilsoniv/pyfaceau
Project-URL: Repository, https://github.com/johnwilsoniv/pyfaceau
Project-URL: Bug Tracker, https://github.com/johnwilsoniv/pyfaceau/issues
Keywords: facial-action-units,openface,computer-vision,facial-analysis,emotion-recognition
Classifier: Development Status :: 5 - Production/Stable
Classifier: Intended Audience :: Science/Research
Classifier: Topic :: Scientific/Engineering :: Artificial Intelligence
Classifier: Topic :: Scientific/Engineering :: Image Recognition
Classifier: License :: Other/Proprietary License
Classifier: Programming Language :: Python :: 3
Classifier: Programming Language :: Python :: 3.10
Classifier: Programming Language :: Python :: 3.11
Classifier: Programming Language :: Python :: 3.12
Classifier: Operating System :: OS Independent
Requires-Python: >=3.10
License-File: LICENSE
Requires-Dist: numpy>=1.20.0
Requires-Dist: opencv-python>=4.5.0
Requires-Dist: pandas>=1.3.0
Requires-Dist: onnxruntime>=1.10.0
Requires-Dist: scipy>=1.7.0
Requires-Dist: scikit-learn>=1.0.0
Requires-Dist: tqdm>=4.62.0
Requires-Dist: pyfhog>=0.1.0
Requires-Dist: pyclnf>=0.2.0
Provides-Extra: dev
Requires-Dist: pytest>=7.0.0; extra == "dev"
Requires-Dist: black>=22.0.0; extra == "dev"
Requires-Dist: flake8>=4.0.0; extra == "dev"
Provides-Extra: accel
Requires-Dist: onnxruntime-coreml>=1.10.0; extra == "accel"
Dynamic: home-page
Dynamic: license-file
Dynamic: requires-python
